qord/__init__.py
qord/_helpers.py
qord/bases.py
qord/enums.py
qord/exceptions.py
qord/project_info.py
qord/utils.py
qord/core/__init__.py
qord/core/cache.py
qord/core/cache_impl.py
qord/core/client.py
qord/core/dispatch.py
qord/core/ratelimits.py
qord/core/rest.py
qord/core/routes.py
qord/core/shard.py
qord/dataclasses/__init__.py
qord/dataclasses/allowed_mentions.py
qord/dataclasses/embeds.py
qord/dataclasses/files.py
qord/dataclasses/message_reference.py
qord/dataclasses/permission_overwrite.py
qord/events/__init__.py
qord/events/base.py
qord/events/base_event.py
qord/events/channels.py
qord/events/emojis.py
qord/events/gateway.py
qord/events/gateway_dispatch.py
qord/events/guild_members.py
qord/events/guilds.py
qord/events/messages.py
qord/events/reactions.py
qord/events/roles.py
qord/events/scheduled_events.py
qord/events/stage_instances.py
qord/events/users.py
qord/flags/__init__.py
qord/flags/base.py
qord/flags/intents.py
qord/flags/messages.py
qord/flags/permissions.py
qord/flags/system_channel.py
qord/flags/users.py
qord/internal/__init__.py
qord/internal/context_managers.py
qord/internal/helpers.py
qord/internal/mixins.py
qord/internal/undefined.py
qord/models/__init__.py
qord/models/base.py
qord/models/channels.py
qord/models/emojis.py
qord/models/guild_members.py
qord/models/guilds.py
qord/models/messages.py
qord/models/roles.py
qord/models/scheduled_events.py
qord/models/stage_instances.py
qord/models/users.py
qord-0.4.0.dist-info/LICENSE
qord-0.4.0.dist-info/METADATA
qord-0.4.0.dist-info/WHEEL
qord-0.4.0.dist-info/top_level.txt
qord-0.4.0.dist-info/RECORD
