Metadata-Version: 2.1
Name: qord
Version: 0.4.0
Summary: Python library for Discord API based around asyncio.
Home-page: https://github.com/nerdguyahmad/qord
Author: nerdguyahmad
License: MIT
Project-URL: Documentation, https://qord.readthedocs.io
Project-URL: Issue tracker, https://github.com/nerdguyahmad/qord/issues
Platform: UNKNOWN
Classifier: Development Status :: 3 - Alpha
Classifier: License :: OSI Approved :: MIT License
Classifier: Intended Audience :: Developers
Classifier: Natural Language :: English
Classifier: Operating System :: OS Independent
Classifier: Programming Language :: Python :: 3.8
Classifier: Programming Language :: Python :: 3.9
Classifier: Topic :: Internet
Classifier: Topic :: Software Development :: Libraries
Classifier: Topic :: Software Development :: Libraries :: Python Modules
Classifier: Topic :: Utilities
Classifier: Typing :: Typed
Requires-Python: >=3.8.0
Requires-Dist: aiohttp (==3.8.1)
